forecaster_toolkit/__init__.py
forecaster_toolkit/data/__init__.py
forecaster_toolkit/data/eda/__init__.py
forecaster_toolkit/data/eda/bivariate_analysis.py
forecaster_toolkit/data/eda/univariate_analysis.py
forecaster_toolkit/data/feature_engineering/__init__.py
forecaster_toolkit/data/feature_engineering/time_features.py
forecaster_toolkit/data/preprocess/__init__.py
forecaster_toolkit/data/preprocess/preprocess_tools.py
forecaster_toolkit/explainability/__init__.py
forecaster_toolkit/explainability/explainability_tools.py
forecaster_toolkit/models/BaseModel.py
forecaster_toolkit/models/__init__.py
forecaster_toolkit/models/dl/DLModel.py
forecaster_toolkit/models/dl/GRU.py
forecaster_toolkit/models/dl/LSTM.py
forecaster_toolkit/models/dl/NBEATS.py
forecaster_toolkit/models/dl/NHITS.py
forecaster_toolkit/models/dl/__init__.py
forecaster_toolkit/models/ml/CatBoost.py
forecaster_toolkit/models/ml/MLModel.py
forecaster_toolkit/models/ml/RandomForest.py
forecaster_toolkit/models/ml/XGBoost.py
forecaster_toolkit/models/ml/__init__.py
forecaster_toolkit/models/model_selection/__init__.py
forecaster_toolkit/models/model_selection/_base_configs.py
forecaster_toolkit/models/model_selection/_model_factory.py
forecaster_toolkit/models/model_selection/hyperparameter_opt.py
forecaster_toolkit/models/model_selection/model_selection.py
forecaster_toolkit/models/statistical/Arima.py
forecaster_toolkit/models/statistical/AutoARIMA.py
forecaster_toolkit/models/statistical/AutoCES.py
forecaster_toolkit/models/statistical/AutoETS.py
forecaster_toolkit/models/statistical/AutoTheta.py
forecaster_toolkit/models/statistical/ETSModel.py
forecaster_toolkit/models/statistical/Prophet.py
forecaster_toolkit/models/statistical/StatisticalModel.py
forecaster_toolkit/models/statistical/__init__.py
forecaster_toolkit/pipeline/__init__.py
forecaster_toolkit/pipeline/pipeline.py
forecaster_toolkit/splitter/__init__.py
forecaster_toolkit/splitter/splitter.py
forecaster_toolkit-0.1.5.dist-info/METADATA
forecaster_toolkit-0.1.5.dist-info/WHEEL
forecaster_toolkit-0.1.5.dist-info/RECORD
