Metadata-Version: 2.3
Name: forecaster-toolkit
Version: 0.1.5
Summary: Python library for time series forecasting
Author: Paul-Adrien Marie
Author-email: paul-adrien.marie@qonto.com
Requires-Python: >=3.12,<3.14
Classifier: Programming Language :: Python :: 3
Classifier: Programming Language :: Python :: 3.12
Classifier: Programming Language :: Python :: 3.13
Requires-Dist: catboost (>=1.2.7)
Requires-Dist: lime (>=0.2.0.1,<0.3.0.0)
Requires-Dist: neuralforecast (>=3.0.0,<4.0.0)
Requires-Dist: numpy (>=1.16.0,<2.0)
Requires-Dist: pmdarima (>=2.0.4,<3.0.0)
Requires-Dist: polars (>=1.22.0,<2.0.0)
Requires-Dist: prophet (>=1.1.6,<2.0.0)
Requires-Dist: pymannkendall (>=1.4.3,<2.0.0)
Requires-Dist: pytest (>=8.3.5,<9.0.0)
Requires-Dist: scikit-learn (>=1.6.1,<2.0.0)
Requires-Dist: shap (>=0.46.0,<0.47.0)
Requires-Dist: sktime (>=0.37.0,<0.38.0)
Requires-Dist: statsforecast (>=2.0.0,<3.0.0)
Requires-Dist: torch (>=2.6.0,<3.0.0)
Requires-Dist: xgboost (>=2.1.4,<3.0.0)
